neural_network_renderer/__init__.py
neural_network_renderer/__main__.py
neural_network_renderer/architecture.py
neural_network_renderer/colors.py
neural_network_renderer/layers.py
neural_network_renderer/styles.py
neural_network_renderer-0.2.1.data/scripts/neural_network_renderer
neural_network_renderer-0.2.1.dist-info/METADATA
neural_network_renderer-0.2.1.dist-info/WHEEL
neural_network_renderer-0.2.1.dist-info/top_level.txt
neural_network_renderer-0.2.1.dist-info/RECORD
