Metadata-Version: 2.1
Name: neural-network-renderer
Version: 0.2.1
Summary: A usefull CNN/DenseNet visualization tool
Home-page: https://github.com/jeandemeusy/neural-network-renderer
Author: Jean Demeusy
Author-email: dev.jdu@gmail.com
License: UNKNOWN
Platform: UNKNOWN
Classifier: Programming Language :: Python :: 3
Classifier: License :: OSI Approved :: MIT License
Classifier: Operating System :: OS Independent
